tinydenticon/__init__.py
tinydenticon/identicon.py
tinydenticon/utils.py
tinydenticon-0.1.2.dist-info/LICENSE
tinydenticon-0.1.2.dist-info/WHEEL
tinydenticon-0.1.2.dist-info/METADATA
tinydenticon-0.1.2.dist-info/RECORD
