Metadata-Version: 2.1
Name: tinydenticon
Version: 0.1.2
Summary: identicon.js compatible Identicon implementation in Python 3
Home-page: https://github.com/tinytengu/tinydenticon
License: GPL-3.0-only
Author: tinytengu
Author-email: tinytengu@yandex.ru
Requires-Python: >=3.10,<4.0
Classifier: License :: OSI Approved :: GNU General Public License v3 (GPLv3)
Classifier: Programming Language :: Python :: 3
Classifier: Programming Language :: Python :: 3.10
Requires-Dist: Pillow (>=9.2.0,<10.0.0)
Requires-Dist: pycryptodomex (>=3.15.0,<4.0.0)
Project-URL: Repository, https://github.com/tinytengu/tinydenticon
